flask_statistics/__init__.py
flask_statistics/utils.py
flask_statistics/templates/flask_statistics_index.html
flask_statistics/templates/flask_statistics_layout.html
flask_statistics/templates/flask_statistics_single_view.html
flask_statistics-1.0.2.dist-info/LICENSE
flask_statistics-1.0.2.dist-info/METADATA
flask_statistics-1.0.2.dist-info/WHEEL
flask_statistics-1.0.2.dist-info/top_level.txt
flask_statistics-1.0.2.dist-info/RECORD
