Metadata-Version: 2.1
Name: flask-statistics
Version: 1.0.2
Summary: Package to collect statistics in Flask.
Home-page: https://github.com/HealYouDown/flask-statistics
Author: HealYouDown
License: UNKNOWN
Platform: UNKNOWN
Classifier: Programming Language :: Python :: 3
Classifier: License :: OSI Approved :: MIT License
Classifier: Operating System :: OS Independent
Requires-Python: >=3.6
